{"is_source_file": true, "format": "JavaScript", "description": "Test setup file for configuring Jest testing environment with custom jest-matchers for DOM assertions, importing @testing-library/jest-dom.", "external_files": ["@testing-library/jest-dom"], "external_methods": [], "published": [], "classes": [], "methods": [], "calls": ["import '@testing-library/jest-dom'"], "search-terms": ["setupTests.js", "jest-dom", "testing-library", "testing setup", "Jest", "React testing"], "state": 2, "file_id": 7, "knowledge_revision": 22, "git_revision": "171507da54808bff8df7494110c1d056ec2e92fc", "ctags": [], "hash": "1a77571e1a8cf36018a41bcedf60db75", "format-version": 4, "code-base-name": "notes_frontend", "filename": "notes_frontend/src/setupTests.js", "revision_history": [{"22": "171507da54808bff8df7494110c1d056ec2e92fc"}]}